tooi/__init__.py
tooi/__main__.py
tooi/app.css
tooi/app.py
tooi/asyncio.py
tooi/cache.py
tooi/cli.py
tooi/commands.py
tooi/context.py
tooi/credentials.py
tooi/entities.py
tooi/goto.py
tooi/http.py
tooi/lorem.py
tooi/messages.py
tooi/settings.py
tooi/api/__init__.py
tooi/api/accounts.py
tooi/api/apps.py
tooi/api/conversations.py
tooi/api/instance.py
tooi/api/notifications.py
tooi/api/search.py
tooi/api/statuses.py
tooi/api/streaming.py
tooi/api/tags.py
tooi/api/timeline.py
tooi/data/__init__.py
tooi/data/accounts.py
tooi/data/apps.py
tooi/data/events.py
tooi/data/instance.py
tooi/data/notifications.py
tooi/data/statuses.py
tooi/data/streaming.py
tooi/data/tags.py
tooi/panes/conversations_pane.py
tooi/panes/search_pane.py
tooi/panes/timeline_pane.py
tooi/screens/__init__.py
tooi/screens/account.py
tooi/screens/accounts_screen.py
tooi/screens/compose.py
tooi/screens/error_box.py
tooi/screens/goto_screen.py
tooi/screens/hashtag_details_modal.py
tooi/screens/instance.py
tooi/screens/loading.py
tooi/screens/main.py
tooi/screens/media.py
tooi/screens/messagebox.py
tooi/screens/modal.py
tooi/screens/source.py
tooi/screens/status_context.py
tooi/utils/__init__.py
tooi/utils/charts.py
tooi/utils/classes.py
tooi/utils/datetime.py
tooi/utils/file.py
tooi/utils/from_dict.py
tooi/utils/html.py
tooi/utils/image.py
tooi/utils/string.py
tooi/utils/temp.py
tooi/widgets/__init__.py
tooi/widgets/account.py
tooi/widgets/chip.py
tooi/widgets/compose.py
tooi/widgets/dialog.py
tooi/widgets/event_detail.py
tooi/widgets/event_list.py
tooi/widgets/gallery.py
tooi/widgets/header.py
tooi/widgets/image.py
tooi/widgets/link.py
tooi/widgets/list_view.py
tooi/widgets/markdown.py
tooi/widgets/menu.py
tooi/widgets/notification_detail.py
tooi/widgets/poll.py
tooi/widgets/status_bar.py
tooi/widgets/status_detail.py
tooi/widgets/form/__init__.py
tooi/widgets/form/federated_select.py
tooi/widgets/form/language_select.py
tooi/widgets/form/select.py
tooi/widgets/form/visibility_select.py
toot_tooi-0.20.0.dist-info/licenses/LICENSE
toot_tooi-0.20.0.dist-info/METADATA
toot_tooi-0.20.0.dist-info/WHEEL
toot_tooi-0.20.0.dist-info/entry_points.txt
toot_tooi-0.20.0.dist-info/top_level.txt
toot_tooi-0.20.0.dist-info/RECORD
