Metadata-Version: 2.4
Name: toot-tooi
Version: 0.20.0
Summary: Mastodon terminal user interface
Author-email: Ivan Habunek <ivan@habunek.com>
License-Expression: MIT
Project-URL: Homepage, https://git.sr.ht/~ihabunek/tooi
Classifier: Programming Language :: Python :: 3
Classifier: Operating System :: OS Independent
Classifier: Environment :: Console
Requires-Python: >=3.11
License-File: LICENSE
Requires-Dist: aiodns
Requires-Dist: aiohttp
Requires-Dist: beautifulsoup4
Requires-Dist: click
Requires-Dist: html2text
Requires-Dist: pillow
Requires-Dist: platformdirs>=4.0.0
Requires-Dist: pydantic~=2.0
Requires-Dist: textual>=7.3.0
Requires-Dist: textual-fspicker>=0.6.0
Requires-Dist: textual-image>=0.7.0
Requires-Dist: tomlkit
Dynamic: license-file
